cognite/osc/__init__.py
cognite/osc/data_pipe.py
cognite/osc/deep_open_classifier.py
cognite/osc/exceptions.py
cognite/osc/open_set_nearest_neighbors.py
cognite/osc/performance_open_set.py
cognite/osc/save_load.py
cognite/osc/trainer.py
cognite/osc/validation.py
cognite_open_set_classifier-0.2.0.dist-info/WHEEL
cognite_open_set_classifier-0.2.0.dist-info/METADATA
cognite_open_set_classifier-0.2.0.dist-info/RECORD
