Metadata-Version: 2.1
Name: cognite-open-set-classifier
Version: 0.2.0
Summary: Open-set classifier
Author: Rebecca Wiborg Seyfarth
Author-email: rebecca.wiborg.seyfarth@cognite.com
Requires-Python: >=3.7,<4.0
Classifier: Programming Language :: Python :: 3
Classifier: Programming Language :: Python :: 3.7
Classifier: Programming Language :: Python :: 3.8
Requires-Dist: dirty-cat (>=0.0.5,<0.0.6)
Requires-Dist: joblib (>=0.14.0,<0.15.0)
Requires-Dist: pandas (>=1.0.3,<2.0.0)
Requires-Dist: scikit-learn (==0.20.3)
Requires-Dist: tensorflow (==2.1.0)
Requires-Dist: tensorflow-estimator (==2.1.0)
